{"repo_full": "ocaml-multicore/ocaml-uring", "org": "ocaml-multicore", "repo_name": "ocaml-uring", "total_weeks": 55, "summaries": [{"week": 44, "year": 2025, "repo": "ocaml-multicore/ocaml-uring", "week_range": "2025-10-27 to 2025-11-02", "start_commit": null, "end_commit": null, "brief_summary": null, "new_features_summary": null, "new_features": null, "activity_summary": null, "activity": null, "discussions_summary": null, "notable_discussions": null, "trends_summary": null, "emerging_trends": null, "issues_summary": null, "good_first_issues": null, "contributors_summary": null, "contributors": null, "org": "ocaml-multicore", "repo_name": "ocaml-uring", "repo_full": "ocaml-multicore/ocaml-uring"}, {"week": 43, "year": 2025, "repo": "ocaml-multicore/ocaml-uring", "week_range": "2025-10-20 to 2025-10-26", "start_commit": null, "end_commit": null, "brief_summary": null, "new_features_summary": null, "new_features": null, "activity_summary": null, "activity": null, "discussions_summary": null, "notable_discussions": null, "trends_summary": null, "emerging_trends": null, "issues_summary": null, "good_first_issues": null, "contributors_summary": null, "contributors": null, "org": "ocaml-multicore", "repo_name": "ocaml-uring", "repo_full": "ocaml-multicore/ocaml-uring"}, {"week": 42, "year": 2025, "repo": "ocaml-multicore/ocaml-uring", "week_range": "2025-10-13 to 2025-10-19", "start_commit": null, "end_commit": null, "brief_summary": null, "new_features_summary": null, "new_features": null, "activity_summary": null, "activity": null, "discussions_summary": null, "notable_discussions": null, "trends_summary": null, "emerging_trends": null, "issues_summary": null, "good_first_issues": null, "contributors_summary": null, "contributors": null, "org": "ocaml-multicore", "repo_name": "ocaml-uring", "repo_full": "ocaml-multicore/ocaml-uring"}, {"week": 41, "year": 2025, "repo": "ocaml-multicore/ocaml-uring", "week_range": "2025-10-06 to 2025-10-12", "start_commit": null, "end_commit": null, "brief_summary": "Design discussions on file descriptor representation and type safety in the OCaml bindings", "new_features_summary": null, "new_features": null, "activity_summary": "Two open PRs exploring file descriptor type safety with active design discussions", "activity": "- [David Allsopp](https://github.com/dra27) opened two PRs exploring **type-safe file descriptor handling** in the library: [#128](https://github.com/ocaml-multicore/ocaml-uring/pull/128) eliminates `Obj.magic` by handling `AT_FDCWD` in C stubs, while draft [#130](https://github.com/ocaml-multicore/ocaml-uring/pull/130) proposes more invasive changes to introduce type-safe wait functions that differentiate between different return types\n- Extended discussion on [#128](https://github.com/ocaml-multicore/ocaml-uring/pull/128) involving [Thomas Leonard](https://github.com/talex5) and [Anil Madhavapeddy](https://github.com/avsm) debated the **abstraction boundaries** between OCaml and C representations of file descriptors, with references to David's blog post on [File descriptors are not integers](https://www.dra27.uk/blog/platform/2025/09/30/file-descriptors-are-not-integers.html) and upstream OCaml PR [ocaml/ocaml#14258](https://github.com/ocaml/ocaml/pull/14258)\n- [Anil Madhavapeddy](https://github.com/avsm) indicated readiness to merge [#128](https://github.com/ocaml-multicore/ocaml-uring/pull/128) pending end-to-end testing with Eio, while discussion continued on optimal approaches for **flambda optimization** of optional arguments and potential deeper integration into the Eio Linux backend", "discussions_summary": "Architecture debate on file descriptor representation and C/OCaml boundary design", "notable_discussions": "- **File descriptor abstraction design** sparked debate on [#128](https://github.com/ocaml-multicore/ocaml-uring/pull/128) about whether OCaml code should access underlying integer representations: [Thomas Leonard](https://github.com/talex5) argued that kernel interfaces require integer access and avoiding it pushes dangerous code into C, while [David Allsopp](https://github.com/dra27) contended that exposing OCaml integer representations is dangerous because they differ from C integers, with [Anil Madhavapeddy](https://github.com/avsm) supporting abstract types with safe conversions for Unix.file_descr, C bindings, and logging\n- **Windows vs Linux portability** briefly discussed on [#128](https://github.com/ocaml-multicore/ocaml-uring/pull/128) and [#130](https://github.com/ocaml-multicore/ocaml-uring/pull/130), with [Anil Madhavapeddy](https://github.com/avsm) noting file descriptors are definitively integers on Linux while genuinely different on Windows, and [David Allsopp](https://github.com/dra27) mentioning Windows ioring differences would warrant a separate library with Eio integration\n- **Compiler optimization** of optional arguments discussed on [#128](https://github.com/ocaml-multicore/ocaml-uring/pull/128), with [David Allsopp](https://github.com/dra27) noting that flambda 1 and 2 optimize optional arguments better than the current approach suggests, prompting plans to refine the implementation", "trends_summary": "Focus on type safety improvements and eliminating unsafe operations", "emerging_trends": "- **Eliminating Obj.magic** usage emerged as a priority across the codebase, with [#128](https://github.com/ocaml-multicore/ocaml-uring/pull/128) and [#130](https://github.com/ocaml-multicore/ocaml-uring/pull/130) both targeting removal of unsafe operations, motivated by upstream work in [ocaml/ocaml#14258](https://github.com/ocaml/ocaml/pull/14258)\n- **Type safety vs allocation trade-offs** became a central design consideration, with discussions on [#130](https://github.com/ocaml-multicore/ocaml-uring/pull/130) exploring how to differentiate return types without increasing allocations on the fast path\n- **Linux-specific optimizations** gaining attention, with [Anil Madhavapeddy](https://github.com/avsm) suggesting on [#128](https://github.com/ocaml-multicore/ocaml-uring/pull/128) that `private int` types for file descriptors and deeper Eio_linux integration could reduce Unix.file_descr usage until necessary", "issues_summary": null, "good_first_issues": null, "contributors_summary": "David Allsopp proposed two type safety PRs with architectural discussions from Thomas Leonard and Anil Madhavapeddy", "contributors": "- [David Allsopp](https://github.com/dra27) authored two PRs exploring file descriptor type safety ([#128](https://github.com/ocaml-multicore/ocaml-uring/pull/128), [#130](https://github.com/ocaml-multicore/ocaml-uring/pull/130)) and provided detailed technical explanations of C/OCaml representation boundaries, calling conventions, and compiler optimization behavior across multiple comments\n- [Anil Madhavapeddy](https://github.com/avsm) reviewed both PRs, provided feedback on abstraction design, discussed integration with Eio Linux backend, and indicated readiness to merge [#128](https://github.com/ocaml-multicore/ocaml-uring/pull/128) pending end-to-end testing\n- [Thomas Leonard](https://github.com/talex5) participated in architectural discussions on [#128](https://github.com/ocaml-multicore/ocaml-uring/pull/128), arguing for OCaml access to file descriptor integers to avoid pushing dangerous code into C, and provided feedback on the trade-offs of different abstraction approaches", "org": "ocaml-multicore", "repo_name": "ocaml-uring", "repo_full": "ocaml-multicore/ocaml-uring"}, {"week": 40, "year": 2025, "repo": "ocaml-multicore/ocaml-uring", "week_range": "2025-09-29 to 2025-10-05", "start_commit": null, "end_commit": null, "brief_summary": "Three PRs opened addressing type safety and eliminating Obj.magic in file descriptor handling", "new_features_summary": null, "new_features": null, "activity_summary": "Type safety improvements for file descriptor handling with alternative approaches under discussion", "activity": "- Three **new PRs opened** this week by [David Allsopp](https://github.com/dra27) focusing on type safety and eliminating unsafe code: type-safe wait functions ([#130](https://github.com/ocaml-multicore/ocaml-uring/pull/130)), safer file descriptor wizardry ([#129](https://github.com/ocaml-multicore/ocaml-uring/pull/129)), and handling `AT_FDCWD` in C to eliminate `Obj.magic` ([#128](https://github.com/ocaml-multicore/ocaml-uring/pull/128))\n- [David Allsopp](https://github.com/dra27) proposed **type-safe wait functions** as a more invasive alternative to address issue [#117](https://github.com/ocaml-multicore/ocaml-uring/issues/117), ensuring OCaml ints only represent actual integers rather than encoded values, with no allocation difference for the fast path and no cost for retrieving `Unix.file_descr` values from syscalls returning descriptors ([#130](https://github.com/ocaml-multicore/ocaml-uring/pull/130))\n- Design discussion emerged around **file descriptor abstraction** between [David Allsopp](https://github.com/dra27) and [Anil Madhavapeddy](https://github.com/avsm) exploring whether file descriptors should be treated as abstract types rather than integers, with [Thomas Leonard](https://github.com/talex5) noting similarities to Eio's existing approach in [ocaml-multicore/eio](https://github.com/ocaml-multicore/eio) ([#130](https://github.com/ocaml-multicore/ocaml-uring/pull/130))\n- Alternative approach in [#129](https://github.com/ocaml-multicore/ocaml-uring/pull/129) provides simpler solution to [#117](https://github.com/ocaml-multicore/ocaml-uring/issues/117) at the cost of an extra C call, currently on hold pending resolution of design discussion in [#130](https://github.com/ocaml-multicore/ocaml-uring/pull/130)", "discussions_summary": "Design debate on treating file descriptors as abstract types versus integers across platforms", "notable_discussions": "- **File descriptor type safety** discussion exploring whether OCaml file descriptors should be abstract types, with [David Allsopp](https://github.com/dra27) noting that while file descriptors are integers on *nix systems, they're not on Windows, and questioning when direct integer access is truly necessary beyond process spawning ([#130](https://github.com/ocaml-multicore/ocaml-uring/pull/130))\n- Platform-specific considerations examined with [David Allsopp](https://github.com/dra27) clarifying that OCaml file descriptors are not integers on Windows though C ones are, while OS-level Windows descriptors are pointers, suggesting `type unix_fd = private int` as a potential solution for Linux-only code like ocaml-uring ([#130](https://github.com/ocaml-multicore/ocaml-uring/pull/130))\n- Potential for **Windows support** raised by [David Allsopp](https://github.com/dra27) noting similarities between liburing and `ioringapi.h`, suggesting ocaml-uring might not need to remain Linux-only ([#130](https://github.com/ocaml-multicore/ocaml-uring/pull/130))", "trends_summary": "Movement toward stronger type safety and elimination of unsafe code patterns", "emerging_trends": "- **Type safety improvements** across the codebase with focus on eliminating `Obj.magic` usage and ensuring proper type representation for system-level abstractions ([#128](https://github.com/ocaml-multicore/ocaml-uring/pull/128), [#129](https://github.com/ocaml-multicore/ocaml-uring/pull/129), [#130](https://github.com/ocaml-multicore/ocaml-uring/pull/130))\n- **Cross-platform considerations** emerging in discussions despite current Linux focus, with exploration of how design decisions might affect potential Windows support ([#130](https://github.com/ocaml-multicore/ocaml-uring/pull/130))\n- **Alignment with Eio ecosystem** continuing as design patterns in ocaml-uring are evaluated against existing Eio implementations, with [Thomas Leonard](https://github.com/talex5) highlighting similar approaches already used in [ocaml-multicore/eio](https://github.com/ocaml-multicore/eio) ([#130](https://github.com/ocaml-multicore/ocaml-uring/pull/130))", "issues_summary": null, "good_first_issues": null, "contributors_summary": "David Allsopp opened three type safety PRs with active design discussions involving Anil Madhavapeddy and Thomas Leonard", "contributors": "- [David Allsopp](https://github.com/dra27) opened three PRs addressing type safety and unsafe code elimination ([#128](https://github.com/ocaml-multicore/ocaml-uring/pull/128), [#129](https://github.com/ocaml-multicore/ocaml-uring/pull/129), [#130](https://github.com/ocaml-multicore/ocaml-uring/pull/130)), participated extensively in design discussions around file descriptor abstraction, and shared related blog post on file descriptor handling across platforms\n- [Anil Madhavapeddy](https://github.com/avsm) engaged in design discussions around file descriptor representation, explored platform-specific considerations for Linux versus Windows, and proposed `type unix_fd = private int` as a potential solution for Linux-only code ([#130](https://github.com/ocaml-multicore/ocaml-uring/pull/130))\n- [Thomas Leonard](https://github.com/talex5) contributed to the design discussion by highlighting similar patterns already implemented in [ocaml-multicore/eio](https://github.com/ocaml-multicore/eio) process handling ([#130](https://github.com/ocaml-multicore/ocaml-uring/pull/130))", "org": "ocaml-multicore", "repo_name": "ocaml-uring", "repo_full": "ocaml-multicore/ocaml-uring"}, {"week": 39, "year": 2025, "repo": "ocaml-multicore/ocaml-uring", "week_range": "2025-09-22 to 2025-09-28", "start_commit": "4876f9f79442691f1baebb68f01b31c70b7f5482", "end_commit": "5f3a7e819bd2ed4bf152bba7391314ede5f960f3", "brief_summary": "Major v2.7.0 release with liburing 2.7 upgrade, new socket operations, and race condition fixes", "new_features_summary": "New socket bind/listen operations, enhanced API documentation, use-after-free fix, and mkdir test improvements", "new_features": "- **Socket bind and listen operations** added with comprehensive OCaml bindings for asynchronous socket binding and listening ([#118](https://github.com/ocaml-multicore/ocaml-uring/issues/118))\n- **Use-after-free data race** fixed in completion queue entry handlers preventing potential memory corruption ([#124](https://github.com/ocaml-multicore/ocaml-uring/issues/124))\n- **Liburing upgrade to version 2.7** bringing new io_uring operations and setup flags with extensive vendor updates ([#118](https://github.com/ocaml-multicore/ocaml-uring/issues/118))\n- **Enhanced API documentation** with detailed parameter descriptions, return value explanations, and usage examples across all interface functions ([#126](https://github.com/ocaml-multicore/ocaml-uring/issues/126))\n- **Fixed mkdir test** to properly mask file permission bits for cross-platform compatibility ([#127](https://github.com/ocaml-multicore/ocaml-uring/issues/127))", "activity_summary": "Release preparation and bug fixes culminating in v2.7.0 with extensive security and functionality improvements", "activity": "- **Version 2.7.0 release** completed by [Anil Madhavapeddy](https://github.com/avsm) including liburing upgrade, socket operations, and comprehensive documentation improvements ([#126](https://github.com/ocaml-multicore/ocaml-uring/issues/126))\n- **Socket operations implementation** merged by [Anil Madhavapeddy](https://github.com/avsm) after extensive testing with Eio test suite and manual verification ([#118](https://github.com/ocaml-multicore/ocaml-uring/issues/118))\n- **Critical data race fix** implemented by [Anil Madhavapeddy](https://github.com/avsm) addressing completion queue entry use-after-free issue identified by [Vesa Karvonen](https://github.com/polytypic) ([#124](https://github.com/ocaml-multicore/ocaml-uring/issues/124), [#123](https://github.com/ocaml-multicore/ocaml-uring/issues/123))\n- **Test infrastructure improvements** by [Thomas Leonard](https://github.com/talex5) fixing mkdir test compatibility issues for opam repository integration ([#127](https://github.com/ocaml-multicore/ocaml-uring/issues/127))", "discussions_summary": "Technical discussions around RPM packaging, ZFS compatibility, and concurrent safety concerns", "notable_discussions": "- **RPM packaging conflict** resolved by [Olaf Hering](https://github.com/olafhering) working with [Thomas Leonard](https://github.com/talex5) to address dlluring.so file conflicts in system package management ([#111](https://github.com/ocaml-multicore/ocaml-uring/issues/111))\n- **ZFS compatibility documentation** improvements suggested by [@toastal](https://github.com/toastal) to help users discover known ZFS kernel version issues with fixed buffers ([#113](https://github.com/ocaml-multicore/ocaml-uring/issues/113))\n- **Concurrent safety analysis** by [Anil Madhavapeddy](https://github.com/avsm) examining potential race conditions in exit implementation, ultimately determined to be handled safely by OCaml wrapper ([#125](https://github.com/ocaml-multicore/ocaml-uring/issues/125))", "trends_summary": "Focus on production readiness through security fixes, enhanced documentation, and comprehensive testing", "emerging_trends": "- **Enhanced production readiness** with focus on race condition elimination and memory safety improvements across the codebase\n- **Comprehensive API documentation** trend showing commitment to developer experience with detailed parameter explanations and usage examples\n- **Cross-platform compatibility** emphasis through improved test infrastructure and packaging considerations for different Linux distributions\n- **Socket operations expansion** indicating broader networking functionality development for io_uring integration", "issues_summary": null, "good_first_issues": null, "contributors_summary": "Anil Madhavapeddy led release work, Thomas Leonard improved tests, Vesa Karvonen identified security issues", "contributors": "- [Anil Madhavapeddy](https://github.com/avsm) implemented socket bind/listen operations ([#118](https://github.com/ocaml-multicore/ocaml-uring/issues/118)), fixed use-after-free data race ([#124](https://github.com/ocaml-multicore/ocaml-uring/issues/124)), prepared v2.7.0 release with enhanced documentation ([#126](https://github.com/ocaml-multicore/ocaml-uring/issues/126)), and analyzed concurrent safety concerns ([#125](https://github.com/ocaml-multicore/ocaml-uring/issues/125))\n- [Thomas Leonard](https://github.com/talex5) fixed mkdir test compatibility issues for cross-platform support ([#127](https://github.com/ocaml-multicore/ocaml-uring/issues/127)) and provided technical guidance on RPM packaging and bytecode backend considerations ([#111](https://github.com/ocaml-multicore/ocaml-uring/issues/111))\n- [Vesa Karvonen](https://github.com/polytypic) identified and reported completion queue entry use-after-free data race vulnerability ([#123](https://github.com/ocaml-multicore/ocaml-uring/issues/123))\n- [Olaf Hering](https://github.com/olafhering) resolved RPM packaging conflicts and improved ELF dependency scanning configuration ([#111](https://github.com/ocaml-multicore/ocaml-uring/issues/111))\n- [@toastal](https://github.com/toastal) suggested documentation improvements for ZFS compatibility issues to enhance user discoverability ([#113](https://github.com/ocaml-multicore/ocaml-uring/issues/113))", "org": "ocaml-multicore", "repo_name": "ocaml-uring", "repo_full": "ocaml-multicore/ocaml-uring"}, {"week": 38, "year": 2025, "repo": "ocaml-multicore/ocaml-uring", "week_range": "2025-09-15 to 2025-09-21", "start_commit": null, "end_commit": null, "brief_summary": null, "new_features_summary": null, "new_features": null, "activity_summary": null, "activity": null, "discussions_summary": null, "notable_discussions": null, "trends_summary": null, "emerging_trends": null, "issues_summary": null, "good_first_issues": null, "contributors_summary": null, "contributors": null, "org": "ocaml-multicore", "repo_name": "ocaml-uring", "repo_full": "ocaml-multicore/ocaml-uring"}, {"week": 37, "year": 2025, "repo": "ocaml-multicore/ocaml-uring", "week_range": "2025-09-08 to 2025-09-14", "start_commit": null, "end_commit": null, "brief_summary": null, "new_features_summary": null, "new_features": null, "activity_summary": null, "activity": null, "discussions_summary": null, "notable_discussions": null, "trends_summary": null, "emerging_trends": null, "issues_summary": null, "good_first_issues": null, "contributors_summary": null, "contributors": null, "org": "ocaml-multicore", "repo_name": "ocaml-uring", "repo_full": "ocaml-multicore/ocaml-uring"}, {"week": 36, "year": 2025, "repo": "ocaml-multicore/ocaml-uring", "week_range": "2025-09-01 to 2025-09-07", "start_commit": "3845f6416aece9e6e1df554a51eee9ea48b41f59", "end_commit": "c95951dbd6984a33e01f17b2e34bad17fb75b8d0", "brief_summary": "Three PRs merged adding Setup_flags API, cleaning up configurator code, and introducing mkdirat function", "new_features_summary": "New Setup_flags module for io_uring configuration and mkdirat function for directory creation", "new_features": "- **Setup_flags module** added enabling fine-grained control over io_uring creation with flags like `single_issuer`, `defer_taskrun`, and `coop_taskrun` ([#122](https://github.com/ocaml-multicore/ocaml-uring/issues/122))\n- **mkdirat function** added to the Uring API for directory creation operations ([#120](https://github.com/ocaml-multicore/ocaml-uring/issues/120))\n- **Enhanced create function** now accepts optional `flags` parameter to customize io_uring behavior using Setup_flags ([#122](https://github.com/ocaml-multicore/ocaml-uring/issues/122))", "activity_summary": "Configurator cleanup merged improving code maintainability with updated primitives header", "activity": "- **Configurator code modernization** by [Thomas Leonard](https://github.com/talex5) cleaning up the build configuration and updating primitives.h for easier future extensions ([#121](https://github.com/ocaml-multicore/ocaml-uring/issues/121))", "discussions_summary": null, "notable_discussions": null, "trends_summary": "Focus on io_uring performance optimization and API expansion for filesystem operations", "emerging_trends": "- **Performance-oriented development** with Setup_flags addressing performance issues in related projects like [ocaml-multicore/eio#788](https://github.com/ocaml-multicore/eio/issues/788) and [axboe/liburing#1452](https://github.com/axboe/liburing/issues/1452)\n- **Filesystem API expansion** with addition of mkdirat showing continued development of file operation support", "issues_summary": null, "good_first_issues": null, "contributors_summary": "Thomas Leonard implemented Setup_flags and configurator improvements, Patrick Ferris added mkdirat functionality", "contributors": "- [Thomas Leonard](https://github.com/talex5) implemented the Setup_flags module with comprehensive io_uring configuration options ([#122](https://github.com/ocaml-multicore/ocaml-uring/issues/122)), modernized the configurator code and updated primitives.h ([#121](https://github.com/ocaml-multicore/ocaml-uring/issues/121)), and provided code review feedback on documentation improvements ([#120](https://github.com/ocaml-multicore/ocaml-uring/issues/120))\n- [Patrick Ferris](https://github.com/patricoferris) contributed the mkdirat function to expand filesystem operation support in the Uring API ([#120](https://github.com/ocaml-multicore/ocaml-uring/issues/120))", "org": "ocaml-multicore", "repo_name": "ocaml-uring", "repo_full": "ocaml-multicore/ocaml-uring"}, {"week": 35, "year": 2025, "repo": "ocaml-multicore/ocaml-uring", "week_range": "2025-08-25 to 2025-08-31", "start_commit": null, "end_commit": null, "brief_summary": null, "new_features_summary": null, "new_features": null, "activity_summary": null, "activity": null, "discussions_summary": null, "notable_discussions": null, "trends_summary": null, "emerging_trends": null, "issues_summary": null, "good_first_issues": null, "contributors_summary": null, "contributors": null, "org": "ocaml-multicore", "repo_name": "ocaml-uring", "repo_full": "ocaml-multicore/ocaml-uring"}, {"week": 34, "year": 2025, "repo": "ocaml-multicore/ocaml-uring", "week_range": "2025-08-18 to 2025-08-24", "start_commit": "7d0b2904e4c0d66b4dae881df4291620e1d78c2a", "end_commit": "7d0b2904e4c0d66b4dae881df4291620e1d78c2a", "brief_summary": "New mkdirat API function added to Uring with directory creation support", "new_features_summary": "Added mkdirat function to Uring API enabling directory creation via io_uring", "new_features": "- **Directory creation support** through new `mkdirat` function in Uring API, allowing asynchronous directory creation with specified permissions and file descriptor reference ([#120](https://github.com/ocaml-multicore/ocaml-uring/issues/120))\n- **Complete API integration** including ML interface, C stubs implementation, and comprehensive test coverage in the test suite ([7d0b290](https://github.com/ocaml-multicore/ocaml-uring/commit/7d0b2904e4c0d66b4dae881df4291620e1d78c2a))", "activity_summary": "Single PR opened for mkdirat functionality implementation", "activity": "- **New PR opened** by [Patrick Ferris](https://github.com/patricoferris) implementing mkdirat API function ([#120](https://github.com/ocaml-multicore/ocaml-uring/issues/120)) with 48 additions across 4 files including ML interface, C bindings, and test coverage", "discussions_summary": null, "notable_discussions": null, "trends_summary": null, "emerging_trends": null, "issues_summary": null, "good_first_issues": null, "contributors_summary": "Patrick Ferris implemented mkdirat API functionality", "contributors": "- [Patrick Ferris](https://github.com/patricoferris) implemented the complete mkdirat functionality including OCaml interface, C stub implementation, and test coverage ([#120](https://github.com/ocaml-multicore/ocaml-uring/issues/120))", "org": "ocaml-multicore", "repo_name": "ocaml-uring", "repo_full": "ocaml-multicore/ocaml-uring"}, {"week": 33, "year": 2025, "repo": "ocaml-multicore/ocaml-uring", "week_range": "2025-08-11 to 2025-08-17", "start_commit": null, "end_commit": null, "brief_summary": null, "new_features_summary": null, "new_features": null, "activity_summary": null, "activity": null, "discussions_summary": null, "notable_discussions": null, "trends_summary": null, "emerging_trends": null, "issues_summary": null, "good_first_issues": null, "contributors_summary": null, "contributors": null, "org": "ocaml-multicore", "repo_name": "ocaml-uring", "repo_full": "ocaml-multicore/ocaml-uring"}, {"week": 32, "year": 2025, "repo": "ocaml-multicore/ocaml-uring", "week_range": "2025-08-04 to 2025-08-10", "start_commit": null, "end_commit": null, "brief_summary": null, "new_features_summary": null, "new_features": null, "activity_summary": null, "activity": null, "discussions_summary": null, "notable_discussions": null, "trends_summary": null, "emerging_trends": null, "issues_summary": null, "good_first_issues": null, "contributors_summary": null, "contributors": null, "org": "ocaml-multicore", "repo_name": "ocaml-uring", "repo_full": "ocaml-multicore/ocaml-uring"}, {"week": 31, "year": 2025, "repo": "ocaml-multicore/ocaml-uring", "week_range": "2025-07-28 to 2025-08-03", "start_commit": null, "end_commit": null, "brief_summary": null, "new_features_summary": null, "new_features": null, "activity_summary": null, "activity": null, "discussions_summary": null, "notable_discussions": null, "trends_summary": null, "emerging_trends": null, "issues_summary": null, "good_first_issues": null, "contributors_summary": null, "contributors": null, "org": "ocaml-multicore", "repo_name": "ocaml-uring", "repo_full": "ocaml-multicore/ocaml-uring"}, {"week": 30, "year": 2025, "repo": "ocaml-multicore/ocaml-uring", "week_range": "2025-07-21 to 2025-07-27", "start_commit": null, "end_commit": null, "brief_summary": null, "new_features_summary": null, "new_features": null, "activity_summary": null, "activity": null, "discussions_summary": null, "notable_discussions": null, "trends_summary": null, "emerging_trends": null, "issues_summary": null, "good_first_issues": null, "contributors_summary": null, "contributors": null, "org": "ocaml-multicore", "repo_name": "ocaml-uring", "repo_full": "ocaml-multicore/ocaml-uring"}, {"week": 29, "year": 2025, "repo": "ocaml-multicore/ocaml-uring", "week_range": "2025-07-14 to 2025-07-20", "start_commit": null, "end_commit": null, "brief_summary": "Issue discussion about ZFS compatibility with fixed buffers received upstream fix information", "new_features_summary": null, "new_features": null, "activity_summary": "Issue discussion about ZFS hanging issue provided information about upstream fix", "activity": "- **Issue discussion** about ZFS compatibility problem where [Thomas Leonard](https://github.com/talex5) received information about upstream fix for hanging with fixed buffers issue ([#113](https://github.com/ocaml-multicore/ocaml-uring/issues/113))", "discussions_summary": null, "notable_discussions": null, "trends_summary": null, "emerging_trends": null, "issues_summary": null, "good_first_issues": null, "contributors_summary": "Thomas Leonard participated in issue discussion about ZFS compatibility fix", "contributors": "- [Thomas Leonard](https://github.com/talex5) participated in discussion about ZFS hanging issue and received information about upstream OpenZFS fix available in versions 2.3.3 and 2.2.8 ([#113](https://github.com/ocaml-multicore/ocaml-uring/issues/113))", "org": "ocaml-multicore", "repo_name": "ocaml-uring", "repo_full": "ocaml-multicore/ocaml-uring"}, {"week": 28, "year": 2025, "repo": "ocaml-multicore/ocaml-uring", "week_range": "2025-07-07 to 2025-07-13", "start_commit": null, "end_commit": null, "brief_summary": null, "new_features_summary": null, "new_features": null, "activity_summary": null, "activity": null, "discussions_summary": null, "notable_discussions": null, "trends_summary": null, "emerging_trends": null, "issues_summary": null, "good_first_issues": null, "contributors_summary": null, "contributors": null, "org": "ocaml-multicore", "repo_name": "ocaml-uring", "repo_full": "ocaml-multicore/ocaml-uring"}, {"week": 27, "year": 2025, "repo": "ocaml-multicore/ocaml-uring", "week_range": "2025-06-30 to 2025-07-06", "start_commit": null, "end_commit": null, "brief_summary": null, "new_features_summary": null, "new_features": null, "activity_summary": null, "activity": null, "discussions_summary": null, "notable_discussions": null, "trends_summary": null, "emerging_trends": null, "issues_summary": null, "good_first_issues": null, "contributors_summary": null, "contributors": null, "org": "ocaml-multicore", "repo_name": "ocaml-uring", "repo_full": "ocaml-multicore/ocaml-uring"}, {"week": 26, "year": 2025, "repo": "ocaml-multicore/ocaml-uring", "week_range": "2025-06-23 to 2025-06-29", "start_commit": null, "end_commit": null, "brief_summary": null, "new_features_summary": null, "new_features": null, "activity_summary": null, "activity": null, "discussions_summary": null, "notable_discussions": null, "trends_summary": null, "emerging_trends": null, "issues_summary": null, "good_first_issues": null, "contributors_summary": null, "contributors": null, "org": "ocaml-multicore", "repo_name": "ocaml-uring", "repo_full": "ocaml-multicore/ocaml-uring"}, {"week": 25, "year": 2025, "repo": "ocaml-multicore/ocaml-uring", "week_range": "2025-06-16 to 2025-06-22", "start_commit": null, "end_commit": null, "brief_summary": null, "new_features_summary": null, "new_features": null, "activity_summary": null, "activity": null, "discussions_summary": null, "notable_discussions": null, "trends_summary": null, "emerging_trends": null, "issues_summary": null, "good_first_issues": null, "contributors_summary": null, "contributors": null, "org": "ocaml-multicore", "repo_name": "ocaml-uring", "repo_full": "ocaml-multicore/ocaml-uring"}, {"week": 24, "year": 2025, "repo": "ocaml-multicore/ocaml-uring", "week_range": "2025-06-09 to 2025-06-15", "start_commit": null, "end_commit": null, "brief_summary": null, "new_features_summary": null, "new_features": null, "activity_summary": null, "activity": null, "discussions_summary": null, "notable_discussions": null, "trends_summary": null, "emerging_trends": null, "issues_summary": null, "good_first_issues": null, "contributors_summary": null, "contributors": null, "org": "ocaml-multicore", "repo_name": "ocaml-uring", "repo_full": "ocaml-multicore/ocaml-uring"}, {"week": 23, "year": 2025, "repo": "ocaml-multicore/ocaml-uring", "week_range": "2025-06-02 to 2025-06-08", "start_commit": null, "end_commit": null, "brief_summary": null, "new_features_summary": null, "new_features": null, "activity_summary": null, "activity": null, "discussions_summary": null, "notable_discussions": null, "trends_summary": null, "emerging_trends": null, "issues_summary": null, "good_first_issues": null, "contributors_summary": null, "contributors": null, "org": "ocaml-multicore", "repo_name": "ocaml-uring", "repo_full": "ocaml-multicore/ocaml-uring"}, {"week": 22, "year": 2025, "repo": "ocaml-multicore/ocaml-uring", "week_range": "2025-05-26 to 2025-06-01", "start_commit": null, "end_commit": null, "brief_summary": null, "new_features_summary": null, "new_features": null, "activity_summary": null, "activity": null, "discussions_summary": null, "notable_discussions": null, "trends_summary": null, "emerging_trends": null, "issues_summary": null, "good_first_issues": null, "contributors_summary": null, "contributors": null, "org": "ocaml-multicore", "repo_name": "ocaml-uring", "repo_full": "ocaml-multicore/ocaml-uring"}, {"week": 21, "year": 2025, "repo": "ocaml-multicore/ocaml-uring", "week_range": "2025-05-19 to 2025-05-25", "start_commit": null, "end_commit": null, "brief_summary": null, "new_features_summary": null, "new_features": null, "activity_summary": null, "activity": null, "discussions_summary": null, "notable_discussions": null, "trends_summary": null, "emerging_trends": null, "issues_summary": null, "good_first_issues": null, "contributors_summary": null, "contributors": null, "org": "ocaml-multicore", "repo_name": "ocaml-uring", "repo_full": "ocaml-multicore/ocaml-uring"}, {"week": 20, "year": 2025, "repo": "ocaml-multicore/ocaml-uring", "week_range": "2025-05-12 to 2025-05-18", "start_commit": null, "end_commit": null, "brief_summary": null, "new_features_summary": null, "new_features": null, "activity_summary": null, "activity": null, "discussions_summary": null, "notable_discussions": null, "trends_summary": null, "emerging_trends": null, "issues_summary": null, "good_first_issues": null, "contributors_summary": null, "contributors": null, "org": "ocaml-multicore", "repo_name": "ocaml-uring", "repo_full": "ocaml-multicore/ocaml-uring"}, {"week": 19, "year": 2025, "repo": "ocaml-multicore/ocaml-uring", "week_range": "2025-05-05 to 2025-05-11", "start_commit": null, "end_commit": null, "brief_summary": null, "new_features_summary": null, "new_features": null, "activity_summary": null, "activity": null, "discussions_summary": null, "notable_discussions": null, "trends_summary": null, "emerging_trends": null, "issues_summary": null, "good_first_issues": null, "contributors_summary": null, "contributors": null, "org": "ocaml-multicore", "repo_name": "ocaml-uring", "repo_full": "ocaml-multicore/ocaml-uring"}, {"week": 18, "year": 2025, "repo": "ocaml-multicore/ocaml-uring", "week_range": "2025-04-28 to 2025-05-04", "start_commit": null, "end_commit": null, "brief_summary": null, "new_features_summary": null, "new_features": null, "activity_summary": null, "activity": null, "discussions_summary": null, "notable_discussions": null, "trends_summary": null, "emerging_trends": null, "issues_summary": null, "good_first_issues": null, "contributors_summary": null, "contributors": null, "org": "ocaml-multicore", "repo_name": "ocaml-uring", "repo_full": "ocaml-multicore/ocaml-uring"}, {"week": 17, "year": 2025, "repo": "ocaml-multicore/ocaml-uring", "week_range": "2025-04-21 to 2025-04-27", "start_commit": null, "end_commit": null, "brief_summary": null, "new_features_summary": null, "new_features": null, "activity_summary": null, "activity": null, "discussions_summary": null, "notable_discussions": null, "trends_summary": null, "emerging_trends": null, "issues_summary": null, "good_first_issues": null, "contributors_summary": null, "contributors": null, "org": "ocaml-multicore", "repo_name": "ocaml-uring", "repo_full": "ocaml-multicore/ocaml-uring"}, {"week": 16, "year": 2025, "repo": "ocaml-multicore/ocaml-uring", "week_range": "2025-04-14 to 2025-04-20", "start_commit": null, "end_commit": null, "brief_summary": null, "new_features_summary": null, "new_features": null, "activity_summary": null, "activity": null, "discussions_summary": null, "notable_discussions": null, "trends_summary": null, "emerging_trends": null, "issues_summary": null, "good_first_issues": null, "contributors_summary": null, "contributors": null, "org": "ocaml-multicore", "repo_name": "ocaml-uring", "repo_full": "ocaml-multicore/ocaml-uring"}, {"week": 15, "year": 2025, "repo": "ocaml-multicore/ocaml-uring", "week_range": "2025-04-07 to 2025-04-13", "start_commit": null, "end_commit": null, "brief_summary": null, "new_features_summary": null, "new_features": null, "activity_summary": null, "activity": null, "discussions_summary": null, "notable_discussions": null, "trends_summary": null, "emerging_trends": null, "issues_summary": null, "good_first_issues": null, "contributors_summary": null, "contributors": null, "org": "ocaml-multicore", "repo_name": "ocaml-uring", "repo_full": "ocaml-multicore/ocaml-uring"}, {"week": 14, "year": 2025, "repo": "ocaml-multicore/ocaml-uring", "week_range": "2025-03-31 to 2025-04-06", "start_commit": null, "end_commit": null, "brief_summary": null, "new_features_summary": null, "new_features": null, "activity_summary": null, "activity": null, "discussions_summary": null, "notable_discussions": null, "trends_summary": null, "emerging_trends": null, "issues_summary": null, "good_first_issues": null, "contributors_summary": null, "contributors": null, "org": "ocaml-multicore", "repo_name": "ocaml-uring", "repo_full": "ocaml-multicore/ocaml-uring"}, {"week": 13, "year": 2025, "repo": "ocaml-multicore/ocaml-uring", "week_range": "2025-03-24 to 2025-03-30", "start_commit": null, "end_commit": null, "brief_summary": null, "new_features_summary": null, "new_features": null, "activity_summary": null, "activity": null, "discussions_summary": null, "notable_discussions": null, "trends_summary": null, "emerging_trends": null, "issues_summary": null, "good_first_issues": null, "contributors_summary": null, "contributors": null, "org": "ocaml-multicore", "repo_name": "ocaml-uring", "repo_full": "ocaml-multicore/ocaml-uring"}, {"week": 12, "year": 2025, "repo": "ocaml-multicore/ocaml-uring", "week_range": "2025-03-17 to 2025-03-23", "start_commit": null, "end_commit": null, "brief_summary": null, "new_features_summary": null, "new_features": null, "activity_summary": null, "activity": null, "discussions_summary": null, "notable_discussions": null, "trends_summary": null, "emerging_trends": null, "issues_summary": null, "good_first_issues": null, "contributors_summary": null, "contributors": null, "org": "ocaml-multicore", "repo_name": "ocaml-uring", "repo_full": "ocaml-multicore/ocaml-uring"}, {"week": 11, "year": 2025, "repo": "ocaml-multicore/ocaml-uring", "week_range": "2025-03-10 to 2025-03-16", "start_commit": null, "end_commit": null, "brief_summary": null, "new_features_summary": null, "new_features": null, "activity_summary": null, "activity": null, "discussions_summary": null, "notable_discussions": null, "trends_summary": null, "emerging_trends": null, "issues_summary": null, "good_first_issues": null, "contributors_summary": null, "contributors": null, "org": "ocaml-multicore", "repo_name": "ocaml-uring", "repo_full": "ocaml-multicore/ocaml-uring"}, {"week": 10, "year": 2025, "repo": "ocaml-multicore/ocaml-uring", "week_range": "2025-03-03 to 2025-03-09", "start_commit": null, "end_commit": null, "brief_summary": null, "new_features_summary": null, "new_features": null, "activity_summary": null, "activity": null, "discussions_summary": null, "notable_discussions": null, "trends_summary": null, "emerging_trends": null, "issues_summary": null, "good_first_issues": null, "contributors_summary": null, "contributors": null, "org": "ocaml-multicore", "repo_name": "ocaml-uring", "repo_full": "ocaml-multicore/ocaml-uring"}, {"week": 9, "year": 2025, "repo": "ocaml-multicore/ocaml-uring", "week_range": "2025-02-24 to 2025-03-02", "start_commit": null, "end_commit": null, "brief_summary": null, "new_features_summary": null, "new_features": null, "activity_summary": null, "activity": null, "discussions_summary": null, "notable_discussions": null, "trends_summary": null, "emerging_trends": null, "issues_summary": null, "good_first_issues": null, "contributors_summary": null, "contributors": null, "org": "ocaml-multicore", "repo_name": "ocaml-uring", "repo_full": "ocaml-multicore/ocaml-uring"}, {"week": 8, "year": 2025, "repo": "ocaml-multicore/ocaml-uring", "week_range": "2025-02-17 to 2025-02-23", "start_commit": null, "end_commit": null, "brief_summary": null, "new_features_summary": null, "new_features": null, "activity_summary": null, "activity": null, "discussions_summary": null, "notable_discussions": null, "trends_summary": null, "emerging_trends": null, "issues_summary": null, "good_first_issues": null, "contributors_summary": null, "contributors": null, "org": "ocaml-multicore", "repo_name": "ocaml-uring", "repo_full": "ocaml-multicore/ocaml-uring"}, {"week": 7, "year": 2025, "repo": "ocaml-multicore/ocaml-uring", "week_range": "2025-02-10 to 2025-02-16", "start_commit": null, "end_commit": null, "brief_summary": null, "new_features_summary": null, "new_features": null, "activity_summary": null, "activity": null, "discussions_summary": null, "notable_discussions": null, "trends_summary": null, "emerging_trends": null, "issues_summary": null, "good_first_issues": null, "contributors_summary": null, "contributors": null, "org": "ocaml-multicore", "repo_name": "ocaml-uring", "repo_full": "ocaml-multicore/ocaml-uring"}, {"week": 6, "year": 2025, "repo": "ocaml-multicore/ocaml-uring", "week_range": "2025-02-03 to 2025-02-09", "start_commit": null, "end_commit": null, "brief_summary": null, "new_features_summary": null, "new_features": null, "activity_summary": null, "activity": null, "discussions_summary": null, "notable_discussions": null, "trends_summary": null, "emerging_trends": null, "issues_summary": null, "good_first_issues": null, "contributors_summary": null, "contributors": null, "org": "ocaml-multicore", "repo_name": "ocaml-uring", "repo_full": "ocaml-multicore/ocaml-uring"}, {"week": 5, "year": 2025, "repo": "ocaml-multicore/ocaml-uring", "week_range": "2025-01-27 to 2025-02-02", "start_commit": null, "end_commit": null, "brief_summary": null, "new_features_summary": null, "new_features": null, "activity_summary": null, "activity": null, "discussions_summary": null, "notable_discussions": null, "trends_summary": null, "emerging_trends": null, "issues_summary": null, "good_first_issues": null, "contributors_summary": null, "contributors": null, "org": "ocaml-multicore", "repo_name": "ocaml-uring", "repo_full": "ocaml-multicore/ocaml-uring"}, {"week": 4, "year": 2025, "repo": "ocaml-multicore/ocaml-uring", "week_range": "2025-01-20 to 2025-01-26", "start_commit": null, "end_commit": null, "brief_summary": null, "new_features_summary": null, "new_features": null, "activity_summary": null, "activity": null, "discussions_summary": null, "notable_discussions": null, "trends_summary": null, "emerging_trends": null, "issues_summary": null, "good_first_issues": null, "contributors_summary": null, "contributors": null, "org": "ocaml-multicore", "repo_name": "ocaml-uring", "repo_full": "ocaml-multicore/ocaml-uring"}, {"week": 3, "year": 2025, "repo": "ocaml-multicore/ocaml-uring", "week_range": "2025-01-13 to 2025-01-19", "start_commit": null, "end_commit": null, "brief_summary": null, "new_features_summary": null, "new_features": null, "activity_summary": null, "activity": null, "discussions_summary": null, "notable_discussions": null, "trends_summary": null, "emerging_trends": null, "issues_summary": null, "good_first_issues": null, "contributors_summary": null, "contributors": null, "org": "ocaml-multicore", "repo_name": "ocaml-uring", "repo_full": "ocaml-multicore/ocaml-uring"}, {"week": 2, "year": 2025, "repo": "ocaml-multicore/ocaml-uring", "week_range": "2025-01-06 to 2025-01-12", "start_commit": null, "end_commit": null, "brief_summary": null, "new_features_summary": null, "new_features": null, "activity_summary": null, "activity": null, "discussions_summary": null, "notable_discussions": null, "trends_summary": null, "emerging_trends": null, "issues_summary": null, "good_first_issues": null, "contributors_summary": null, "contributors": null, "org": "ocaml-multicore", "repo_name": "ocaml-uring", "repo_full": "ocaml-multicore/ocaml-uring"}, {"week": 1, "year": 2025, "repo": "ocaml-multicore/ocaml-uring", "week_range": "2024-12-30 to 2025-01-05", "start_commit": null, "end_commit": null, "brief_summary": null, "new_features_summary": null, "new_features": null, "activity_summary": null, "activity": null, "discussions_summary": null, "notable_discussions": null, "trends_summary": null, "emerging_trends": null, "issues_summary": null, "good_first_issues": null, "contributors_summary": null, "contributors": null, "org": "ocaml-multicore", "repo_name": "ocaml-uring", "repo_full": "ocaml-multicore/ocaml-uring"}, {"week": 52, "year": 2024, "repo": "ocaml-multicore/ocaml-uring", "week_range": "2024-12-23 to 2024-12-29", "start_commit": null, "end_commit": null, "brief_summary": null, "new_features_summary": null, "new_features": null, "activity_summary": null, "activity": null, "discussions_summary": null, "notable_discussions": null, "trends_summary": null, "emerging_trends": null, "issues_summary": null, "good_first_issues": null, "contributors_summary": null, "contributors": null, "org": "ocaml-multicore", "repo_name": "ocaml-uring", "repo_full": "ocaml-multicore/ocaml-uring"}, {"week": 51, "year": 2024, "repo": "ocaml-multicore/ocaml-uring", "week_range": "2024-12-16 to 2024-12-22", "start_commit": null, "end_commit": null, "brief_summary": null, "new_features_summary": null, "new_features": null, "activity_summary": null, "activity": null, "discussions_summary": null, "notable_discussions": null, "trends_summary": null, "emerging_trends": null, "issues_summary": null, "good_first_issues": null, "contributors_summary": null, "contributors": null, "org": "ocaml-multicore", "repo_name": "ocaml-uring", "repo_full": "ocaml-multicore/ocaml-uring"}, {"week": 50, "year": 2024, "repo": "ocaml-multicore/ocaml-uring", "week_range": "2024-12-09 to 2024-12-15", "start_commit": null, "end_commit": null, "brief_summary": null, "new_features_summary": null, "new_features": null, "activity_summary": null, "activity": null, "discussions_summary": null, "notable_discussions": null, "trends_summary": null, "emerging_trends": null, "issues_summary": null, "good_first_issues": null, "contributors_summary": null, "contributors": null, "org": "ocaml-multicore", "repo_name": "ocaml-uring", "repo_full": "ocaml-multicore/ocaml-uring"}, {"week": 49, "year": 2024, "repo": "ocaml-multicore/ocaml-uring", "week_range": "2024-12-02 to 2024-12-08", "start_commit": null, "end_commit": null, "brief_summary": null, "new_features_summary": null, "new_features": null, "activity_summary": null, "activity": null, "discussions_summary": null, "notable_discussions": null, "trends_summary": null, "emerging_trends": null, "issues_summary": null, "good_first_issues": null, "contributors_summary": null, "contributors": null, "org": "ocaml-multicore", "repo_name": "ocaml-uring", "repo_full": "ocaml-multicore/ocaml-uring"}, {"week": 48, "year": 2024, "repo": "ocaml-multicore/ocaml-uring", "week_range": "2024-11-25 to 2024-12-01", "start_commit": null, "end_commit": null, "brief_summary": "Issue #119 debugging hang in _io_uring_get_cqe resolved as not a bug in ocaml-uring", "new_features_summary": null, "new_features": null, "activity_summary": "Single issue closure involving debugging assistance for io_uring hang", "activity": "- Issue debugging session where [Krzysztof Leśniak](https://github.com/serpent7776) reported a hang in `_io_uring_get_cqe` and [Thomas Leonard](https://github.com/talex5) provided troubleshooting guidance and closed the issue ([#119](https://github.com/ocaml-multicore/ocaml-uring/issues/119))", "discussions_summary": null, "notable_discussions": null, "trends_summary": null, "emerging_trends": null, "issues_summary": null, "good_first_issues": null, "contributors_summary": "Two contributors involved in issue resolution", "contributors": "- [Krzysztof Leśniak](https://github.com/serpent7776) reported a debugging issue with a long-running program experiencing a hang in the io_uring library ([#119](https://github.com/ocaml-multicore/ocaml-uring/issues/119))\n- [Thomas Leonard](https://github.com/talex5) provided detailed debugging guidance with stack trace analysis and alternative testing approaches, concluding the issue was not a bug in ocaml-uring ([#119](https://github.com/ocaml-multicore/ocaml-uring/issues/119))", "org": "ocaml-multicore", "repo_name": "ocaml-uring", "repo_full": "ocaml-multicore/ocaml-uring"}, {"week": 47, "year": 2024, "repo": "ocaml-multicore/ocaml-uring", "week_range": "2024-11-18 to 2024-11-24", "start_commit": null, "end_commit": null, "brief_summary": "Issue reported about random hang in io_uring completion queue handling with debugging guidance provided", "new_features_summary": null, "new_features": null, "activity_summary": "Single issue opened about io_uring hang with community debugging support", "activity": "- [Krzysztof Leśniak](https://github.com/serpent7776) reported a **random hang issue** in `_io_uring_get_cqe` affecting long-running programs using cohttp-eio and Eio.Time.sleep_until ([#119](https://github.com/ocaml-multicore/ocaml-uring/issues/119))\n- [Thomas Leonard](https://github.com/talex5) provided **debugging guidance** with tracing recommendations using OCAML_RUNTIME_EVENTS for diagnosing the hang condition ([#119](https://github.com/ocaml-multicore/ocaml-uring/issues/119))", "discussions_summary": "Technical discussion about diagnosing io_uring hangs using runtime event tracing", "notable_discussions": "- **Debugging approach** discussion for diagnosing io_uring hangs where [Thomas Leonard](https://github.com/talex5) recommended using `eio-trace record` with OCAML_RUNTIME_EVENTS configuration to capture event traces for analysis ([#119](https://github.com/ocaml-multicore/ocaml-uring/issues/119))", "trends_summary": null, "emerging_trends": null, "issues_summary": null, "good_first_issues": null, "contributors_summary": "Two contributors involved: issue reporting and community debugging support", "contributors": "- [Krzysztof Leśniak](https://github.com/serpent7776) reported a detailed issue with GDB stack trace showing random hang behavior in production long-running application ([#119](https://github.com/ocaml-multicore/ocaml-uring/issues/119))\n- [Thomas Leonard](https://github.com/talex5) provided comprehensive debugging guidance including specific tracing commands and runtime event configuration for diagnosing the hang condition ([#119](https://github.com/ocaml-multicore/ocaml-uring/issues/119))", "org": "ocaml-multicore", "repo_name": "ocaml-uring", "repo_full": "ocaml-multicore/ocaml-uring"}, {"week": 46, "year": 2024, "repo": "ocaml-multicore/ocaml-uring", "week_range": "2024-11-11 to 2024-11-17", "start_commit": null, "end_commit": null, "brief_summary": null, "new_features_summary": null, "new_features": null, "activity_summary": null, "activity": null, "discussions_summary": null, "notable_discussions": null, "trends_summary": null, "emerging_trends": null, "issues_summary": null, "good_first_issues": null, "contributors_summary": null, "contributors": null, "org": "ocaml-multicore", "repo_name": "ocaml-uring", "repo_full": "ocaml-multicore/ocaml-uring"}, {"week": 45, "year": 2024, "repo": "ocaml-multicore/ocaml-uring", "week_range": "2024-11-04 to 2024-11-10", "start_commit": null, "end_commit": null, "brief_summary": null, "new_features_summary": null, "new_features": null, "activity_summary": null, "activity": null, "discussions_summary": null, "notable_discussions": null, "trends_summary": null, "emerging_trends": null, "issues_summary": null, "good_first_issues": null, "contributors_summary": null, "contributors": null, "org": "ocaml-multicore", "repo_name": "ocaml-uring", "repo_full": "ocaml-multicore/ocaml-uring"}, {"week": 44, "year": 2024, "repo": "ocaml-multicore/ocaml-uring", "week_range": "2024-10-28 to 2024-11-03", "start_commit": null, "end_commit": null, "brief_summary": null, "new_features_summary": null, "new_features": null, "activity_summary": null, "activity": null, "discussions_summary": null, "notable_discussions": null, "trends_summary": null, "emerging_trends": null, "issues_summary": null, "good_first_issues": null, "contributors_summary": null, "contributors": null, "org": "ocaml-multicore", "repo_name": "ocaml-uring", "repo_full": "ocaml-multicore/ocaml-uring"}, {"week": 43, "year": 2024, "repo": "ocaml-multicore/ocaml-uring", "week_range": "2024-10-21 to 2024-10-27", "start_commit": null, "end_commit": null, "brief_summary": null, "new_features_summary": null, "new_features": null, "activity_summary": null, "activity": null, "discussions_summary": null, "notable_discussions": null, "trends_summary": null, "emerging_trends": null, "issues_summary": null, "good_first_issues": null, "contributors_summary": null, "contributors": null, "org": "ocaml-multicore", "repo_name": "ocaml-uring", "repo_full": "ocaml-multicore/ocaml-uring"}, {"week": 42, "year": 2024, "repo": "ocaml-multicore/ocaml-uring", "week_range": "2024-10-14 to 2024-10-20", "start_commit": null, "end_commit": null, "brief_summary": null, "new_features_summary": null, "new_features": null, "activity_summary": null, "activity": null, "discussions_summary": null, "notable_discussions": null, "trends_summary": null, "emerging_trends": null, "issues_summary": null, "good_first_issues": null, "contributors_summary": null, "contributors": null, "org": "ocaml-multicore", "repo_name": "ocaml-uring", "repo_full": "ocaml-multicore/ocaml-uring"}]}